Metadata-Version: 2.1
Name: sausage-bot-dev
Version: 3.6.3.dev23
Summary: A highly customisable Discord bot
Home-page: https://github.com/jackson147/Red-DiscordBot
Author: Jaswahhihi
License: GPL-3.0
Project-URL: Documentation, https://docs.discord.red
Project-URL: Donate on Patreon, https://www.patreon.com/Red_Devs
Project-URL: Issue Tracker, https://github.com/jackson147/Red-DiscordBot/issues
Project-URL: Source Code, https://github.com/jackson147/Red-DiscordBot
Platform: UNKNOWN
Classifier: Development Status :: 5 - Production/Stable
Classifier: Framework :: AsyncIO
Classifier: Intended Audience :: Developers
Classifier: Intended Audience :: End Users/Desktop
Classifier: License :: OSI Approved :: GNU General Public License v3 (GPLv3)
Classifier: Natural Language :: English
Classifier: Operating System :: MacOS :: MacOS X
Classifier: Operating System :: Microsoft :: Windows
Classifier: Operating System :: POSIX :: Linux
Classifier: Programming Language :: Python :: 3.8
Classifier: Topic :: Communications :: Chat
Requires-Python: <3.9,>=3.8.1
License-File: LICENSE
License-File: redbot/vendored/discord-ext-menus.LICENSE
Requires-Dist: aiohttp (==3.7.3)
Requires-Dist: aiohttp-json-rpc (==0.13.3)
Requires-Dist: aiosqlite (==0.16.1)
Requires-Dist: appdirs (==1.4.4)
Requires-Dist: apsw-wheels (==3.34.1.post1)
Requires-Dist: async-timeout (==3.0.1)
Requires-Dist: attrs (==20.3.0)
Requires-Dist: Babel (==2.9.0)
Requires-Dist: chardet (==3.0.4)
Requires-Dist: click (==7.1.2)
Requires-Dist: colorama (==0.4.4)
Requires-Dist: commonmark (==0.9.1)
Requires-Dist: contextlib2 (==0.6.0.post1)
Requires-Dist: discord.py (==1.7.3)
Requires-Dist: fuzzywuzzy (==0.18.0)
Requires-Dist: idna (==2.10)
Requires-Dist: Markdown (==3.3.3)
Requires-Dist: multidict (==5.1.0)
Requires-Dist: psutil (==5.8.0)
Requires-Dist: PyNaCl (==1.3.0)
Requires-Dist: Pygments (==2.7.4)
Requires-Dist: python-dateutil (==2.8.1)
Requires-Dist: python-Levenshtein-wheels (==0.13.2)
Requires-Dist: pytz (==2021.1)
Requires-Dist: PyYAML (==5.4.1)
Requires-Dist: Red-Lavalink (==0.8.1)
Requires-Dist: rich (==9.9.0)
Requires-Dist: schema (==0.7.4)
Requires-Dist: six (==1.15.0)
Requires-Dist: typing-extensions (==3.7.4.3)
Requires-Dist: yarl (==1.6.3)
Requires-Dist: uvloop (==0.15.0) ; sys_platform != "win32" and platform_python_implementation == "CPython"
Requires-Dist: distro (==1.5.0) ; sys_platform == "linux"
Provides-Extra: all
Requires-Dist: asyncpg (==0.22.0) ; extra == 'all'
Provides-Extra: dev
Requires-Dist: asyncpg (==0.22.0) ; extra == 'dev'
Requires-Dist: alabaster (==0.7.12) ; extra == 'dev'
Requires-Dist: certifi (==2020.12.5) ; extra == 'dev'
Requires-Dist: docutils (==0.16) ; extra == 'dev'
Requires-Dist: imagesize (==1.2.0) ; extra == 'dev'
Requires-Dist: Jinja2 (==2.11.3) ; extra == 'dev'
Requires-Dist: MarkupSafe (==1.1.1) ; extra == 'dev'
Requires-Dist: packaging (==20.9) ; extra == 'dev'
Requires-Dist: pyparsing (==2.4.7) ; extra == 'dev'
Requires-Dist: requests (==2.25.1) ; extra == 'dev'
Requires-Dist: snowballstemmer (==2.1.0) ; extra == 'dev'
Requires-Dist: Sphinx (==3.4.3) ; extra == 'dev'
Requires-Dist: sphinx-prompt (==1.4.0) ; extra == 'dev'
Requires-Dist: sphinx-rtd-theme (==0.5.1) ; extra == 'dev'
Requires-Dist: sphinxcontrib-applehelp (==1.0.2) ; extra == 'dev'
Requires-Dist: sphinxcontrib-devhelp (==1.0.2) ; extra == 'dev'
Requires-Dist: sphinxcontrib-htmlhelp (==1.0.3) ; extra == 'dev'
Requires-Dist: sphinxcontrib-jsmath (==1.0.1) ; extra == 'dev'
Requires-Dist: sphinxcontrib-qthelp (==1.0.3) ; extra == 'dev'
Requires-Dist: sphinxcontrib-serializinghtml (==1.1.4) ; extra == 'dev'
Requires-Dist: sphinxcontrib-trio (==1.1.2) ; extra == 'dev'
Requires-Dist: urllib3 (==1.26.3) ; extra == 'dev'
Requires-Dist: black (==20.8b1) ; extra == 'dev'
Requires-Dist: mypy-extensions (==0.4.3) ; extra == 'dev'
Requires-Dist: pathspec (==0.8.1) ; extra == 'dev'
Requires-Dist: regex (==2020.11.13) ; extra == 'dev'
Requires-Dist: toml (==0.10.2) ; extra == 'dev'
Requires-Dist: typed-ast (==1.4.2) ; extra == 'dev'
Requires-Dist: astroid (==2.4.2) ; extra == 'dev'
Requires-Dist: iniconfig (==1.1.1) ; extra == 'dev'
Requires-Dist: isort (==5.7.0) ; extra == 'dev'
Requires-Dist: lazy-object-proxy (==1.4.3) ; extra == 'dev'
Requires-Dist: mccabe (==0.6.1) ; extra == 'dev'
Requires-Dist: pluggy (==0.13.1) ; extra == 'dev'
Requires-Dist: py (==1.10.0) ; extra == 'dev'
Requires-Dist: pylint (==2.6.0) ; extra == 'dev'
Requires-Dist: pytest (==6.2.2) ; extra == 'dev'
Requires-Dist: pytest-asyncio (==0.14.0) ; extra == 'dev'
Requires-Dist: pytest-mock (==3.5.1) ; extra == 'dev'
Requires-Dist: wrapt (==1.12.1) ; extra == 'dev'
Provides-Extra: docs
Requires-Dist: alabaster (==0.7.12) ; extra == 'docs'
Requires-Dist: certifi (==2020.12.5) ; extra == 'docs'
Requires-Dist: docutils (==0.16) ; extra == 'docs'
Requires-Dist: imagesize (==1.2.0) ; extra == 'docs'
Requires-Dist: Jinja2 (==2.11.3) ; extra == 'docs'
Requires-Dist: MarkupSafe (==1.1.1) ; extra == 'docs'
Requires-Dist: packaging (==20.9) ; extra == 'docs'
Requires-Dist: pyparsing (==2.4.7) ; extra == 'docs'
Requires-Dist: requests (==2.25.1) ; extra == 'docs'
Requires-Dist: snowballstemmer (==2.1.0) ; extra == 'docs'
Requires-Dist: Sphinx (==3.4.3) ; extra == 'docs'
Requires-Dist: sphinx-prompt (==1.4.0) ; extra == 'docs'
Requires-Dist: sphinx-rtd-theme (==0.5.1) ; extra == 'docs'
Requires-Dist: sphinxcontrib-applehelp (==1.0.2) ; extra == 'docs'
Requires-Dist: sphinxcontrib-devhelp (==1.0.2) ; extra == 'docs'
Requires-Dist: sphinxcontrib-htmlhelp (==1.0.3) ; extra == 'docs'
Requires-Dist: sphinxcontrib-jsmath (==1.0.1) ; extra == 'docs'
Requires-Dist: sphinxcontrib-qthelp (==1.0.3) ; extra == 'docs'
Requires-Dist: sphinxcontrib-serializinghtml (==1.1.4) ; extra == 'docs'
Requires-Dist: sphinxcontrib-trio (==1.1.2) ; extra == 'docs'
Requires-Dist: urllib3 (==1.26.3) ; extra == 'docs'
Provides-Extra: postgres
Requires-Dist: asyncpg (==0.22.0) ; extra == 'postgres'
Provides-Extra: style
Requires-Dist: black (==20.8b1) ; extra == 'style'
Requires-Dist: mypy-extensions (==0.4.3) ; extra == 'style'
Requires-Dist: pathspec (==0.8.1) ; extra == 'style'
Requires-Dist: regex (==2020.11.13) ; extra == 'style'
Requires-Dist: toml (==0.10.2) ; extra == 'style'
Requires-Dist: typed-ast (==1.4.2) ; extra == 'style'
Provides-Extra: test
Requires-Dist: astroid (==2.4.2) ; extra == 'test'
Requires-Dist: iniconfig (==1.1.1) ; extra == 'test'
Requires-Dist: isort (==5.7.0) ; extra == 'test'
Requires-Dist: lazy-object-proxy (==1.4.3) ; extra == 'test'
Requires-Dist: mccabe (==0.6.1) ; extra == 'test'
Requires-Dist: packaging (==20.9) ; extra == 'test'
Requires-Dist: pluggy (==0.13.1) ; extra == 'test'
Requires-Dist: py (==1.10.0) ; extra == 'test'
Requires-Dist: pylint (==2.6.0) ; extra == 'test'
Requires-Dist: pyparsing (==2.4.7) ; extra == 'test'
Requires-Dist: pytest (==6.2.2) ; extra == 'test'
Requires-Dist: pytest-asyncio (==0.14.0) ; extra == 'test'
Requires-Dist: pytest-mock (==3.5.1) ; extra == 'test'
Requires-Dist: toml (==0.10.2) ; extra == 'test'
Requires-Dist: wrapt (==1.12.1) ; extra == 'test'
